{
  "elements": [
    {
      "faces": {
        "north": {
          "texture": "#chalk_dust",
          "uv": [
            16.0,
            0.0,
            0.0,
            16.0
          ]
        },
        "south": {
          "texture": "#chalk_dust"
        }
      },
      "from": [
        0,
        0,
        0.1
      ],
      "to": [
        16,
        16,
        0.1
      ]
    }
  ],
  "render_type": "minecraft:translucent",
  "textures": {
    "chalk_dust": "remix:block/chalk_dust",
    "particle": "remix:block/chalk_dust"
  }
}